iFCon/__init__.py
iFCon/iFCon.py
iFCon/iFConFile.py
ifcon-3.0.dist-info/licenses/LICENSE
ifcon-3.0.dist-info/METADATA
ifcon-3.0.dist-info/WHEEL
ifcon-3.0.dist-info/entry_points.txt
ifcon-3.0.dist-info/top_level.txt
ifcon-3.0.dist-info/RECORD
