Metadata-Version: 2.4
Name: iFCon
Version: 3.0
Summary: A tool for handling iFAction resource files (iFCon files)
Home-page: https://github.com/eWloYW8/iFCon
Author: eWloYW8
Author-email: thenextone200612@gmail.com
License: GPLv3
Classifier: Programming Language :: Python :: 3
Classifier: License :: OSI Approved :: GNU General Public License v3 (GPLv3)
Classifier: Operating System :: OS Independent
Requires-Python: >=3.6
License-File: LICENSE
Dynamic: author
Dynamic: author-email
Dynamic: classifier
Dynamic: description
Dynamic: description-content-type
Dynamic: home-page
Dynamic: license
Dynamic: license-file
Dynamic: requires-python
Dynamic: summary
